configflow/__init__.py
configflow/exceptions/__init__.py
configflow/exceptions/misc.py
configflow/exceptions/providers.py
configflow/exceptions/sources.py
configflow/misc/__init__.py
configflow/misc/decorators.py
configflow/misc/dictionary.py
configflow/misc/string.py
configflow/providers/__init__.py
configflow/providers/dotenv.py
configflow/providers/factory.py
configflow/providers/ini.py
configflow/providers/properties.py
configflow/providers/toml.py
configflow/providers/yaml.py
configflow/py.typed
configflow/sources/__init__.py
configflow/sources/abstract.py
configflow/sources/file.py
configflow-0.4.0.dist-info/LICENSE
configflow-0.4.0.dist-info/WHEEL
configflow-0.4.0.dist-info/METADATA
configflow-0.4.0.dist-info/RECORD
