Metadata-Version: 2.1
Name: configflow
Version: 0.4.0
Summary: configflow - is the configuration management library for Python.
Home-page: https://configflow.readthedocs.io/en/latest
License: BSD-3-Clause
Keywords: json,yaml,toml,dotenv,ini,cfg,properties,vault,environment,command-line,pydantic,setup,config,configuration,settings,management,python,pypi,cross-platform,hacktoberfest
Author: Volodymyr Pivoshenko
Author-email: volodymyr.pivoshenko@gmail.com
Maintainer: Volodymyr Pivoshenko
Maintainer-email: volodymyr.pivoshenko@gmail.com
Requires-Python: >=3.7,<3.10
Classifier: Development Status :: 1 - Planning
Classifier: Environment :: Other Environment
Classifier: Intended Audience :: Developers
Classifier: Intended Audience :: Information Technology
Classifier: License :: OSI Approved :: BSD License
Classifier: Natural Language :: English
Classifier: Operating System :: OS Independent
Classifier: Programming Language :: Python
Classifier: Programming Language :: Python :: 3
Classifier: Programming Language :: Python :: 3.7
Classifier: Programming Language :: Python :: 3.8
Classifier: Programming Language :: Python :: 3.9
Classifier: Topic :: Scientific/Engineering
Classifier: Topic :: Software Development
Classifier: Topic :: Software Development :: Libraries
Classifier: Topic :: Software Development :: Libraries :: Python Modules
Provides-Extra: dotenv
Provides-Extra: toml
Provides-Extra: yaml
Requires-Dist: PyYAML (>=6.0,<7.0); extra == "yaml"
Requires-Dist: awesome-pattern-matching (>=0.24.2,<0.25.0)
Requires-Dist: decorator (>=5.1.1,<6.0.0)
Requires-Dist: python-dotenv (>=0.20.0,<0.21.0); extra == "dotenv"
Requires-Dist: toml (>=0.10.2,<0.11.0); extra == "toml"
Requires-Dist: typing-extensions (>=4.2.0,<5.0.0)
Project-URL: Documentation, https://configflow.readthedocs.io/en/latest
Project-URL: Issues, https://github.com/volopivoshenko/configflow/issues
Project-URL: Repository, https://github.com/volopivoshenko/configflow
Project-URL: Releases, https://github.com/volopivoshenko/configflow/releases
Project-URL: Say Thanks!, https://www.buymeacoffee.com/volopivoshenko
